oidc-0.1.6.dist-info/METADATA
oidc-0.1.6.dist-info/RECORD
oidc-0.1.6.dist-info/WHEEL
oidc-0.1.6.dist-info/top_level.txt
oidc-0.1.6.dist-info/DESCRIPTION.rst
oidc-0.1.6.dist-info/metadata.json
oidc/errors.py
oidc/hybridflow.py
oidc/userinfo.py
oidc/__init__.py
oidc/idtoken.py
oidc/authorizationcodeflow.py
oidc/interfaces.py
oidc/provider.py
oidc/implicitflow.py
oidc/tests/test_implicitflow.py
oidc/tests/test_hybridflow.py
oidc/tests/test_authorizationcodeflow.py
oidc/tests/__init__.py
oidc/tests/test_provider.py
