Metadata-Version: 2.0
Name: oidc
Version: 0.1.6
Summary: OpenID Connect library for Python 3.
Home-page: https://github.com/GehirnInc/python-oidc
Author: Kohei YOSHIDA
Author-email: kohei.yoshida@gehirn.co.jp
License: The MIT License (MIT) Copyright © 2014 Kohei YOSHIDA <kohei.yoshida@gehirn.co.jp>
Requires-Dist: py3oauth2 (>=0.4.5,<0.5)
Requires-Dist: jwt (>=0.3.2,<0.4)
